{
  "app": {
    "[project]/app/_not-found/page": [
      "static/media/Helvetica-s.p.8248aa15.ttf",
      "static/media/Helvetica_Bold-s.p.3e411a3d.ttf"
    ],
    "[project]/app/page": [
      "static/media/Helvetica-s.p.8248aa15.ttf",
      "static/media/Helvetica_Bold-s.p.3e411a3d.ttf"
    ],
    "[project]/app/contact-us/page": [
      "static/media/Helvetica-s.p.8248aa15.ttf",
      "static/media/Helvetica_Bold-s.p.3e411a3d.ttf"
    ],
    "[project]/app/products/page": [
      "static/media/Helvetica-s.p.8248aa15.ttf",
      "static/media/Helvetica_Bold-s.p.3e411a3d.ttf"
    ]
  },
  "appUsingSizeAdjust": true,
  "pages": {},
  "pagesUsingSizeAdjust": false
}